loggerTest/__init__.py
loggerTest/static/README.md
loggerTest/static/description.yaml
loggerTest/static/index.js
loggerTest-0.0.11.dist-info/METADATA
loggerTest-0.0.11.dist-info/WHEEL
loggerTest-0.0.11.dist-info/top_level.txt
loggerTest-0.0.11.dist-info/RECORD
