Metadata-Version: 2.1
Name: loggerTest
Version: 0.0.11
Summary: 課前測試版本
Home-page: https://github.com/lairuilin/logger_test
Author: lairuilin
Author-email: kalai850531@g.ncu.edu.tw
License: MIT
Platform: UNKNOWN
Requires-Dist: jupyter
